<annotation><filename>003270.png</filename><folder>VOC2012</folder><segmented>0</segmented><size><depth>3</depth><width>1242</width><height>375</height></size><source><annotation>Dummy</annotation><database>Dummy</database><image>Dummy</image></source><object><name>car</name><difficult>0</difficult><occluded>0</occluded><truncated>0</truncated><pose>Unspecified</pose><bndbox><xmin>572.02</xmin><xmax>618.26</xmax><ymin>177.92</ymin><ymax>214.39</ymax></bndbox></object><object><name>car</name><difficult>0</difficult><occluded>0</occluded><truncated>0</truncated><pose>Unspecified</pose><bndbox><xmin>1218.47</xmin><xmax>1242.0</xmax><ymin>189.93</ymin><ymax>375.0</ymax></bndbox></object><object><name>car</name><difficult>0</difficult><occluded>0</occluded><truncated>0</truncated><pose>Unspecified</pose><bndbox><xmin>489.75</xmin><xmax>535.37</xmax><ymin>171.92</ymin><ymax>202.91</ymax></bndbox></object></annotation>