<annotation><filename>003267.png</filename><folder>VOC2012</folder><segmented>0</segmented><size><depth>3</depth><width>1242</width><height>375</height></size><source><annotation>Dummy</annotation><database>Dummy</database><image>Dummy</image></source><object><name>car</name><difficult>0</difficult><occluded>0</occluded><truncated>0</truncated><pose>Unspecified</pose><bndbox><xmin>1.0</xmin><xmax>235.38</xmax><ymin>179.93</ymin><ymax>289.45</ymax></bndbox></object><object><name>car</name><difficult>0</difficult><occluded>0</occluded><truncated>0</truncated><pose>Unspecified</pose><bndbox><xmin>51.13</xmin><xmax>284.5</xmax><ymin>181.44</ymin><ymax>279.89</ymax></bndbox></object><object><name>car</name><difficult>0</difficult><occluded>0</occluded><truncated>0</truncated><pose>Unspecified</pose><bndbox><xmin>234.61</xmin><xmax>334.53</xmax><ymin>184.78</ymin><ymax>241.01</ymax></bndbox></object><object><name>car</name><difficult>0</difficult><occluded>0</occluded><truncated>0</truncated><pose>Unspecified</pose><bndbox><xmin>271.69</xmin><xmax>404.54</xmax><ymin>183.07</ymin><ymax>234.54</ymax></bndbox></object><object><name>car</name><difficult>0</difficult><occluded>0</occluded><truncated>0</truncated><pose>Unspecified</pose><bndbox><xmin>426.83</xmin><xmax>474.11</xmax><ymin>180.62</ymin><ymax>214.86</ymax></bndbox></object><object><name>car</name><difficult>0</difficult><occluded>0</occluded><truncated>0</truncated><pose>Unspecified</pose><bndbox><xmin>444.39</xmin><xmax>488.18</xmax><ymin>180.47</ymin><ymax>209.12</ymax></bndbox></object><object><name>person</name><difficult>0</difficult><occluded>0</occluded><truncated>0</truncated><pose>Unspecified</pose><bndbox><xmin>402.87</xmin><xmax>415.21</xmax><ymin>182.33</ymin><ymax>230.68</ymax></bndbox></object><object><name>person</name><difficult>0</difficult><occluded>0</occluded><truncated>0</truncated><pose>Unspecified</pose><bndbox><xmin>396.47</xmin><xmax>410.8</xmax><ymin>195.05</ymin><ymax>229.44</ymax></bndbox></object></annotation>