<annotation><filename>003329.png</filename><folder>VOC2012</folder><segmented>0</segmented><size><depth>3</depth><width>1242</width><height>375</height></size><source><annotation>Dummy</annotation><database>Dummy</database><image>Dummy</image></source><object><name>person</name><difficult>0</difficult><occluded>0</occluded><truncated>0</truncated><pose>Unspecified</pose><bndbox><xmin>161.21</xmin><xmax>210.5</xmax><ymin>161.07</ymin><ymax>291.23</ymax></bndbox></object><object><name>person</name><difficult>0</difficult><occluded>0</occluded><truncated>0</truncated><pose>Unspecified</pose><bndbox><xmin>740.77</xmin><xmax>757.87</xmax><ymin>163.42</ymin><ymax>230.84</ymax></bndbox></object></annotation>