<annotation><filename>003353.png</filename><folder>VOC2012</folder><segmented>0</segmented><size><depth>3</depth><width>1242</width><height>375</height></size><source><annotation>Dummy</annotation><database>Dummy</database><image>Dummy</image></source><object><name>car</name><difficult>0</difficult><occluded>0</occluded><truncated>0</truncated><pose>Unspecified</pose><bndbox><xmin>1.0</xmin><xmax>168.87</xmax><ymin>218.35</ymin><ymax>375.0</ymax></bndbox></object><object><name>car</name><difficult>0</difficult><occluded>0</occluded><truncated>0</truncated><pose>Unspecified</pose><bndbox><xmin>686.04</xmin><xmax>775.85</xmax><ymin>189.28</ymin><ymax>249.34</ymax></bndbox></object><object><name>car</name><difficult>0</difficult><occluded>0</occluded><truncated>0</truncated><pose>Unspecified</pose><bndbox><xmin>967.98</xmin><xmax>1158.71</xmax><ymin>165.13</ymin><ymax>241.87</ymax></bndbox></object><object><name>car</name><difficult>0</difficult><occluded>0</occluded><truncated>0</truncated><pose>Unspecified</pose><bndbox><xmin>672.78</xmin><xmax>734.72</xmax><ymin>184.71</ymin><ymax>232.73</ymax></bndbox></object><object><name>car</name><difficult>0</difficult><occluded>0</occluded><truncated>0</truncated><pose>Unspecified</pose><bndbox><xmin>477.84</xmin><xmax>527.86</xmax><ymin>186.03</ymin><ymax>221.6</ymax></bndbox></object><object><name>car</name><difficult>0</difficult><occluded>0</occluded><truncated>0</truncated><pose>Unspecified</pose><bndbox><xmin>853.42</xmin><xmax>1001.9</xmax><ymin>176.97</ymin><ymax>224.46</ymax></bndbox></object><object><name>car</name><difficult>0</difficult><occluded>0</occluded><truncated>0</truncated><pose>Unspecified</pose><bndbox><xmin>911.28</xmin><xmax>1073.5</xmax><ymin>175.99</ymin><ymax>233.64</ymax></bndbox></object><object><name>car</name><difficult>0</difficult><occluded>0</occluded><truncated>0</truncated><pose>Unspecified</pose><bndbox><xmin>657.38</xmin><xmax>682.66</xmax><ymin>179.04</ymin><ymax>204.19</ymax></bndbox></object><object><name>car</name><difficult>0</difficult><occluded>0</occluded><truncated>0</truncated><pose>Unspecified</pose><bndbox><xmin>948.78</xmin><xmax>1242.0</xmax><ymin>220.76</ymin><ymax>375.0</ymax></bndbox></object></annotation>